{
  "schema": "1.0",
  "comment": "This file maps proto services/RPCs to the corresponding library clients/methods",
  "language": "csharp",
  "protoPackage": "google.storage.control.v2",
  "libraryPackage": "Google.Cloud.Storage.Control.V2",
  "services": {
    "StorageControl": {
      "clients": {
        "grpc": {
          "libraryClient": "StorageControlClient",
          "rpcs": {
            "CreateFolder": {
              "methods": [
                "CreateFolder",
                "CreateFolderAsync"
              ]
            },
            "DeleteFolder": {
              "methods": [
                "DeleteFolder",
                "DeleteFolderAsync"
              ]
            },
            "GetFolder": {
              "methods": [
                "GetFolder",
                "GetFolderAsync"
              ]
            },
            "GetStorageLayout": {
              "methods": [
                "GetStorageLayout",
                "GetStorageLayoutAsync"
              ]
            },
            "ListFolders": {
              "methods": [
                "ListFolders",
                "ListFoldersAsync"
              ]
            },
            "RenameFolder": {
              "methods": [
                "RenameFolder",
                "RenameFolderAsync"
              ]
            }
          }
        }
      }
    }
  }
}
