{
  "schema": "1.0",
  "comment": "This file maps proto services/RPCs to the corresponding library clients/methods",
  "language": "csharp",
  "protoPackage": "google.longrunning",
  "libraryPackage": "Google.LongRunning",
  "services": {
    "Operations": {
      "clients": {
        "grpc": {
          "libraryClient": "OperationsClient",
          "rpcs": {
            "CancelOperation": {
              "methods": [
                "CancelOperation",
                "CancelOperationAsync"
              ]
            },
            "DeleteOperation": {
              "methods": [
                "DeleteOperation",
                "DeleteOperationAsync"
              ]
            },
            "GetOperation": {
              "methods": [
                "GetOperation",
                "GetOperationAsync"
              ]
            },
            "ListOperations": {
              "methods": [
                "ListOperations",
                "ListOperationsAsync"
              ]
            },
            "WaitOperation": {
              "methods": [
                "WaitOperation",
                "WaitOperationAsync"
              ]
            }
          }
        }
      }
    }
  }
}
